bw_aggregation/__init__.py
bw_aggregation/calculator.py
bw_aggregation/errors.py
bw_aggregation/estimator.py
bw_aggregation/main.py
bw_aggregation/override.py
bw_aggregation/utils.py
bw_aggregation-1.1.dist-info/LICENSE
bw_aggregation-1.1.dist-info/METADATA
bw_aggregation-1.1.dist-info/WHEEL
bw_aggregation-1.1.dist-info/top_level.txt
bw_aggregation-1.1.dist-info/RECORD
