Metadata-Version: 2.1
Name: bw_aggregation
Version: 1.1
Summary: Use aggregated processes for quicker calculations
Author-email: bw_aggregation <cmutel@gmail.com>
Maintainer-email: bw_aggregation <cmutel@gmail.com>
Project-URL: source, https://github.com/brightway-lca/bw_aggregation
Project-URL: homepage, https://github.com/brightway-lca/bw_aggregation
Project-URL: tracker, https://github.com/brightway-lca/bw_aggregation/issues
Classifier: Development Status :: 4 - Beta
Classifier: Programming Language :: Python
Classifier: Programming Language :: Python :: 3
Classifier: Programming Language :: Python :: 3.9
Classifier: Programming Language :: Python :: 3.10
Classifier: Programming Language :: Python :: 3.11
Classifier: Programming Language :: Python :: 3.12
Classifier: Natural Language :: English
Classifier: Operating System :: OS Independent
Classifier: Topic :: Scientific/Engineering
Requires-Python: >=3.9
License-File: LICENSE
Requires-Dist: bw2calc >1.99
Requires-Dist: bw2data >=4.0.dev36
Requires-Dist: bw-graph-tools >=0.3.1
Requires-Dist: bw-processing >=0.9.3
Requires-Dist: fs
Requires-Dist: matrix-utils
Requires-Dist: numpy <2
Provides-Extra: dev
Requires-Dist: build ; extra == 'dev'
Requires-Dist: pre-commit ; extra == 'dev'
Requires-Dist: pylint ; extra == 'dev'
Requires-Dist: pytest ; extra == 'dev'
Requires-Dist: pytest-cov ; extra == 'dev'
Requires-Dist: pytest-randomly ; extra == 'dev'
Requires-Dist: setuptools ; extra == 'dev'
Provides-Extra: testing
Requires-Dist: bw-aggregation ; extra == 'testing'
Requires-Dist: pytest ; extra == 'testing'
Requires-Dist: pytest-cov ; extra == 'testing'
Requires-Dist: python-coveralls ; extra == 'testing'
